task_dispatcher/__init__.py
task_dispatcher/__main__.py
task_dispatcher/celery_app.py
task_dispatcher/consts.py
task_dispatcher/config/__init__.py
task_dispatcher/config/celeryconfig.py
task_dispatcher/config/settings.py
task_dispatcher/consumers/paper_match.py
task_dispatcher/mq/__init__.py
task_dispatcher/mq/consumer.py
task_dispatcher/mq/consumer_manager.py
task_dispatcher/mq/sender.py
task_dispatcher/mq_v1/__init__.py
task_dispatcher/mq_v1/config.py
task_dispatcher/mq_v1/consumer.py
task_dispatcher/mq_v1/consumer_manager.py
task_dispatcher/mq_v1/sender.py
task_dispatcher/services/__init__.py
task_dispatcher/services/a.py
task_dispatcher/tasks/__init__.py
task_dispatcher/tasks/base.py
task_dispatcher/tasks/tasks.py
data_process_task_dispatcher-0.0.0.dist-info/METADATA
data_process_task_dispatcher-0.0.0.dist-info/WHEEL
data_process_task_dispatcher-0.0.0.dist-info/entry_points.txt
data_process_task_dispatcher-0.0.0.dist-info/RECORD
