Metadata-Version: 2.4
Name: data_process_task_dispatcher
Version: 0.0.0
Summary: A well-structured Celery project
Requires-Python: >=3.12
Requires-Dist: aio-pika>=9.5.5
Requires-Dist: celery>=5.3.0
Requires-Dist: flower>=2.0.0
Requires-Dist: poethepoet>=0.36.0
Requires-Dist: pydantic-settings>=2.10.1
Requires-Dist: python-dotenv>=1.0.0
Requires-Dist: redis>=5.0.0
Requires-Dist: sqlmodel>=0.0.24
Provides-Extra: release
Requires-Dist: poethepoet>=0.36.0; extra == 'release'
Requires-Dist: python-semantic-release>=10.2.0; extra == 'release'
